pyrepl_hacks/__init__.py
pyrepl_hacks/_types.py
pyrepl_hacks/bind_utils.py
pyrepl_hacks/command_utils.py
pyrepl_hacks/commands.py
pyrepl_hacks/key_utils.py
pyrepl_hacks/py.typed
pyrepl_hacks/theme_utils.py
pyrepl_hacks-0.4.0.dist-info/licenses/LICENSE
pyrepl_hacks-0.4.0.dist-info/METADATA
pyrepl_hacks-0.4.0.dist-info/WHEEL
pyrepl_hacks-0.4.0.dist-info/top_level.txt
pyrepl_hacks-0.4.0.dist-info/RECORD
