Metadata-Version: 2.4
Name: pyrepl-hacks
Version: 0.4.0
Summary: Hacky extensions and helper functions for the new Python REPL.
Author: Trey Hunner
License-Expression: MIT
Project-URL: Documentation, https://github.com/treyhunner/pyrepl-hacks#readme
Project-URL: Issues, https://github.com/treyhunner/pyrepl-hacks/issues
Project-URL: Source, https://github.com/treyhunner/pyrepl-hacks
Keywords: repl,python,terminal,keyboard,shortcuts,commands
Classifier: Development Status :: 3 - Alpha
Classifier: Environment :: Console
Classifier: Intended Audience :: Developers
Classifier: Operating System :: OS Independent
Classifier: Programming Language :: Python :: 3
Classifier: Programming Language :: Python :: 3.13
Classifier: Programming Language :: Python :: 3.14
Classifier: Programming Language :: Python :: 3 :: Only
Classifier: Topic :: Software Development :: Libraries :: Python Modules
Classifier: Topic :: System :: Shells
Classifier: Topic :: Terminals
Classifier: Typing :: Typed
Requires-Python: <3.15,>=3.13
License-File: LICENSE
Dynamic: license-file
